properties_diff/__init__.py
properties_diff/diff.py
properties_diff/patch.py
properties_diff/utils.py
properties_diff-0.4.1.dist-info/entry_points.txt
properties_diff-0.4.1.dist-info/LICENSE
properties_diff-0.4.1.dist-info/WHEEL
properties_diff-0.4.1.dist-info/METADATA
properties_diff-0.4.1.dist-info/RECORD
